voxelgym2D/__init__.py
voxelgym2D/version.txt
voxelgym2D/envs/__init__.py
voxelgym2D/envs/base_env.py
voxelgym2D/envs/env_one_step.py
voxelgym2D/envs/maps/600x600.npy
voxelgym2D-0.3.2.post1.dist-info/LICENSE
voxelgym2D-0.3.2.post1.dist-info/METADATA
voxelgym2D-0.3.2.post1.dist-info/WHEEL
voxelgym2D-0.3.2.post1.dist-info/top_level.txt
voxelgym2D-0.3.2.post1.dist-info/RECORD
