Metadata-Version: 2.1
Name: voxelgym2D
Version: 0.3.2.post1
Summary: Gym environment for 2D grid path planning
Home-page: https://github.com/harisankar95/voxelgym2D.git
Author: Harisankar Babu
Author-email: harisankar995@gmail.com
License: MIT
Keywords: reinforcement-learning,machine-learning,gym,openai,python,gymnasium
Platform: any
Classifier: Development Status :: 3 - Alpha
Classifier: Intended Audience :: Education
Classifier: License :: OSI Approved :: MIT License
Classifier: Natural Language :: English
Classifier: Operating System :: OS Independent
Classifier: Programming Language :: Python :: 3.8
Classifier: Topic :: Scientific/Engineering :: Artificial Intelligence
Requires-Python: >=3.8
Requires-Dist: gymnasium <=0.29.1
Requires-Dist: numpy
Requires-Dist: scikit-image <=0.22.0
Requires-Dist: opencv-python
Requires-Dist: pathfinding >=1.0.9
Requires-Dist: matplotlib
Provides-Extra: dev
Requires-Dist: pytest ; extra == 'dev'
Requires-Dist: coverage ; extra == 'dev'
Requires-Dist: pylint ; extra == 'dev'
Requires-Dist: mypy ; extra == 'dev'
Requires-Dist: isort ; extra == 'dev'
Requires-Dist: black ; extra == 'dev'
Requires-Dist: tox >=4.5.0 ; extra == 'dev'
Provides-Extra: docs
Requires-Dist: sphinx ; extra == 'docs'
Requires-Dist: sphinx-rtd-theme ; extra == 'docs'
Requires-Dist: myst-parser ; extra == 'docs'
Requires-Dist: sphinx-autodoc-typehints ; extra == 'docs'
Requires-Dist: sphinx-copybutton ; extra == 'docs'
Requires-Dist: sphinx-prompt ; extra == 'docs'
Requires-Dist: sphinx-notfound-page ; extra == 'docs'
Provides-Extra: sb3
Requires-Dist: stable-baselines3[extra] >=2.0.0 ; extra == 'sb3'
Requires-Dist: sb3-contrib >=2.0.0 ; extra == 'sb3'
Requires-Dist: rl-zoo3 >=2.0.0 ; extra == 'sb3'
